<?xml version="1.0" encoding="utf-8"?>
<LanguageData>
  <!--The following translations were generated by https://www.deepl.com/-->
  <!-- EN: poison buildup -->
  <PoisonBuildup.label>Giftanhäufung</PoisonBuildup.label>
  <PoisonBuildup.description>Giftanhäufung</PoisonBuildup.description>
  <!-- EN: initial-hidden -->
  <PoisonBuildup.stages.initialhidden.label>initial-versteckt</PoisonBuildup.stages.initialhidden.label>
  <!-- EN: initial -->
  <PoisonBuildup.stages.initial.label>anfänglich</PoisonBuildup.stages.initial.label>
  <!-- EN: minor -->
  <PoisonBuildup.stages.minor.label>kleinere</PoisonBuildup.stages.minor.label>
  <!-- EN: moderate -->
  <PoisonBuildup.stages.moderate.label>mäßig</PoisonBuildup.stages.moderate.label>
  <!-- EN: serious -->
  <PoisonBuildup.stages.serious.label>seriös</PoisonBuildup.stages.serious.label>
  <!-- EN: extreme -->
  <PoisonBuildup.stages.extreme.label>extrem</PoisonBuildup.stages.extreme.label>
</LanguageData>
