<?xml version="1.0" encoding="utf-8"?>
<LanguageData>
  <!--The following translations were generated by https://www.deepl.com/-->
  <!-- EN: sword fern -->
  <SwordFern.label>Schwertfarn</SwordFern.label>
  <!-- EN: Sword fern populates the understory of moist coniferous forests at low elevations. It grows best in a well-drained acidic soil of rich humus and small stones. -->
  <SwordFern.description>Schwertfarn bevölkert das Unterholz von feuchten Nadelwäldern in niedrigen Lagen. Er wächst am besten in einem gut durchlässigen, sauren Boden mit viel Humus und kleinen Steinen.</SwordFern.description>
  <!-- EN: redcedar tree -->
  <TreeCedar.label>Rotzederbaum</TreeCedar.label>
  <!-- EN: Native to the temperate rainforests, redcedar is a riprarian tree, growing in many forested swamps and streambanks. -->
  <TreeCedar.description>Die in den gemäßigten Regenwäldern beheimatete Rotzeder ist ein riprarer Baum, der in vielen bewaldeten Sümpfen und an Flussufern wächst.</TreeCedar.description>
</LanguageData>
